subs2cia/CardExport.py
subs2cia/Common.py
subs2cia/__init__.py
subs2cia/__main__.py
subs2cia/argparser.py
subs2cia/cli.py
subs2cia/condense.py
subs2cia/ffmpeg_tools.py
subs2cia/main.py
subs2cia/pickers.py
subs2cia/sources.py
subs2cia/subtools.py
subs2cia/subzipper.py
subs2cia-0.5.0.dist-info/METADATA
subs2cia-0.5.0.dist-info/RECORD
subs2cia-0.5.0.dist-info/WHEEL
subs2cia-0.5.0.dist-info/entry_points.txt
subs2cia-0.5.0.dist-info/top_level.txt
