Metadata-Version: 2.1
Name: subs2cia
Version: 0.5.0
Summary: A subtitle-based multimedia extractor and compressor
Home-page: https://github.com/dxing97/subs2cia
Author: Daniel Xing
Author-email: danielxing97@gmail.com
License: MIT
Platform: UNKNOWN
Classifier: Programming Language :: Python :: 3
Classifier: License :: OSI Approved :: MIT License
Classifier: Operating System :: OS Independent
Requires-Python: >=3.6
Requires-Dist: ffmpeg-python
Requires-Dist: pycountry
Requires-Dist: pysubs2
Requires-Dist: tqdm
Requires-Dist: tqdm
Requires-Dist: gevent
Requires-Dist: colorlog
